CHANGES.txt
CONTRIBUTORS.txt
MANIFEST.in
README.txt
setup.py
eggs/z3c.recipe.scripts-1.0.1-py2.6.egg/EGG-INFO/SOURCES.txt
eggs/z3c.recipe.scripts-1.0.1-py2.6.egg/EGG-INFO/dependency_links.txt
eggs/z3c.recipe.scripts-1.0.1-py2.6.egg/EGG-INFO/entry_points.txt
eggs/z3c.recipe.scripts-1.0.1-py2.6.egg/EGG-INFO/namespace_packages.txt
eggs/z3c.recipe.scripts-1.0.1-py2.6.egg/EGG-INFO/requires.txt
eggs/z3c.recipe.scripts-1.0.1-py2.6.egg/EGG-INFO/top_level.txt
eggs/z3c.recipe.scripts-1.0.1-py2.6.egg/z3c/recipe/scripts/README.txt
eggs/zc.buildout-1.5.2-py2.6.egg/README.txt
eggs/zc.buildout-1.5.2-py2.6.egg/EGG-INFO/SOURCES.txt
eggs/zc.buildout-1.5.2-py2.6.egg/EGG-INFO/dependency_links.txt
eggs/zc.buildout-1.5.2-py2.6.egg/EGG-INFO/entry_points.txt
eggs/zc.buildout-1.5.2-py2.6.egg/EGG-INFO/namespace_packages.txt
eggs/zc.buildout-1.5.2-py2.6.egg/EGG-INFO/requires.txt
eggs/zc.buildout-1.5.2-py2.6.egg/EGG-INFO/top_level.txt
eggs/zc.buildout-1.5.2-py2.6.egg/zc/buildout/allowhosts.txt
eggs/zc.buildout-1.5.2-py2.6.egg/zc/buildout/bootstrap.txt
eggs/zc.buildout-1.5.2-py2.6.egg/zc/buildout/buildout.txt
eggs/zc.buildout-1.5.2-py2.6.egg/zc/buildout/debugging.txt
eggs/zc.buildout-1.5.2-py2.6.egg/zc/buildout/dependencylinks.txt
eggs/zc.buildout-1.5.2-py2.6.egg/zc/buildout/distribute.txt
eggs/zc.buildout-1.5.2-py2.6.egg/zc/buildout/download.txt
eggs/zc.buildout-1.5.2-py2.6.egg/zc/buildout/downloadcache.txt
eggs/zc.buildout-1.5.2-py2.6.egg/zc/buildout/easy_install.txt
eggs/zc.buildout-1.5.2-py2.6.egg/zc/buildout/extends-cache.txt
eggs/zc.buildout-1.5.2-py2.6.egg/zc/buildout/repeatable.txt
eggs/zc.buildout-1.5.2-py2.6.egg/zc/buildout/runsetup.txt
eggs/zc.buildout-1.5.2-py2.6.egg/zc/buildout/setup.txt
eggs/zc.buildout-1.5.2-py2.6.egg/zc/buildout/testing.txt
eggs/zc.buildout-1.5.2-py2.6.egg/zc/buildout/testing_bugfix.txt
eggs/zc.buildout-1.5.2-py2.6.egg/zc/buildout/unzip.txt
eggs/zc.buildout-1.5.2-py2.6.egg/zc/buildout/update.txt
eggs/zc.buildout-1.5.2-py2.6.egg/zc/buildout/upgrading_distribute.txt
eggs/zc.buildout-1.5.2-py2.6.egg/zc/buildout/virtualenv.txt
eggs/zc.buildout-1.5.2-py2.6.egg/zc/buildout/windows.txt
eggs/zc.recipe.egg-1.3.2-py2.6.egg/EGG-INFO/SOURCES.txt
eggs/zc.recipe.egg-1.3.2-py2.6.egg/EGG-INFO/dependency_links.txt
eggs/zc.recipe.egg-1.3.2-py2.6.egg/EGG-INFO/entry_points.txt
eggs/zc.recipe.egg-1.3.2-py2.6.egg/EGG-INFO/namespace_packages.txt
eggs/zc.recipe.egg-1.3.2-py2.6.egg/EGG-INFO/requires.txt
eggs/zc.recipe.egg-1.3.2-py2.6.egg/EGG-INFO/top_level.txt
eggs/zc.recipe.egg-1.3.2-py2.6.egg/zc/recipe/egg/README.txt
eggs/zc.recipe.egg-1.3.2-py2.6.egg/zc/recipe/egg/api.txt
eggs/zc.recipe.egg-1.3.2-py2.6.egg/zc/recipe/egg/custom.txt
eggs/zc.recipe.egg-1.3.2-py2.6.egg/zc/recipe/egg/selecting-python.txt
eggs/zope.exceptions-3.6.1-py2.6.egg/EGG-INFO/SOURCES.txt
eggs/zope.exceptions-3.6.1-py2.6.egg/EGG-INFO/dependency_links.txt
eggs/zope.exceptions-3.6.1-py2.6.egg/EGG-INFO/namespace_packages.txt
eggs/zope.exceptions-3.6.1-py2.6.egg/EGG-INFO/requires.txt
eggs/zope.exceptions-3.6.1-py2.6.egg/EGG-INFO/top_level.txt
eggs/zope.testing-3.10.2-py2.6.egg/EGG-INFO/SOURCES.txt
eggs/zope.testing-3.10.2-py2.6.egg/EGG-INFO/dependency_links.txt
eggs/zope.testing-3.10.2-py2.6.egg/EGG-INFO/namespace_packages.txt
eggs/zope.testing-3.10.2-py2.6.egg/EGG-INFO/requires.txt
eggs/zope.testing-3.10.2-py2.6.egg/EGG-INFO/top_level.txt
eggs/zope.testing-3.10.2-py2.6.egg/zope/testing/doctest.txt
eggs/zope.testing-3.10.2-py2.6.egg/zope/testing/formparser.txt
eggs/zope.testing-3.10.2-py2.6.egg/zope/testing/module.txt
eggs/zope.testing-3.10.2-py2.6.egg/zope/testing/setupstack.txt
eggs/zope.testrunner-4.0.1-py2.6.egg/EGG-INFO/SOURCES.txt
eggs/zope.testrunner-4.0.1-py2.6.egg/EGG-INFO/dependency_links.txt
eggs/zope.testrunner-4.0.1-py2.6.egg/EGG-INFO/entry_points.txt
eggs/zope.testrunner-4.0.1-py2.6.egg/EGG-INFO/namespace_packages.txt
eggs/zope.testrunner-4.0.1-py2.6.egg/EGG-INFO/requires.txt
eggs/zope.testrunner-4.0.1-py2.6.egg/EGG-INFO/top_level.txt
eggs/zope.testrunner-4.0.1-py2.6.egg/zope/testrunner/testrunner-arguments.txt
web2pyrecipe.egg-info/PKG-INFO
web2pyrecipe.egg-info/SOURCES.txt
web2pyrecipe.egg-info/dependency_links.txt
web2pyrecipe.egg-info/entry_points.txt
web2pyrecipe.egg-info/namespace_packages.txt
web2pyrecipe.egg-info/not-zip-safe
web2pyrecipe.egg-info/requires.txt
web2pyrecipe.egg-info/top_level.txt
