Metadata-Version: 1.0
Name: web2pyrecipe
Version: 1.0.1
Summary: A web2py recipe for buildout.
Home-page: http://http://github.com/douglascamata/web2pyrecipe
Author: Douglas Camata
Author-email: d.camata@gmail.com
License: ZPL
Platform: UNKNOWN
Classifier: Framework :: Buildout
Classifier: Intended Audience :: Developers
Classifier: Topic :: Software Development :: Build Tools
Classifier: License :: OSI Approved :: Zope Public License
